LICENSE
__init__.py
color_diff.py
conf_diff.py
html_format.py
conf_diff-0.6.5.dist-info/LICENSE
conf_diff-0.6.5.dist-info/WHEEL
conf_diff-0.6.5.dist-info/METADATA
conf_diff-0.6.5.dist-info/RECORD
