Metadata-Version: 2.1
Name: conf-diff
Version: 0.6.5
Summary: compare configuration files
Home-page: https://github.com/muhammad-rafi/conf_diff
License: MIT
Author: Muhammad Rafi
Author-email: murafi@cisco.com
Requires-Python: >=3.8,<4.0
Classifier: License :: OSI Approved :: MIT License
Classifier: Programming Language :: Python :: 3
Classifier: Programming Language :: Python :: 3.10
Classifier: Programming Language :: Python :: 3.8
Classifier: Programming Language :: Python :: 3.9
Requires-Dist: colorama (>=0.4.4,<0.5.0)
Requires-Dist: importlib-metadata (>=1.0,<2.0); python_version >= "3.8"
Project-URL: Repository, https://github.com/muhammad-rafi/conf_diff
